[
	{
		"spray":
		{
			"id": "329460",
			"exportable": "Sim",
			"recommendation": "Sim",
			"initDate": "2021-07-13 06:00",
			"endDate": "2021-07-16 14:00",
			"subplots": "Armazém",
			"area": "0",
			"volume": "",
			"product": "",
			"quantity": "",
			"dosage": "",
			"concentration": "",
			"ground": "",
			"activeSubs": "",
			"notes":"",
			"updatedAt": "2021-07-15 16:18",
			"updatedBy": "Pedro Lourenço"
		}
	},
	{
		"spray":
		{
			"id": "410479",
			"exportable": "Sim",
			"recommendation": "Sim",
			"initDate": "2021-10-14 08:00",
			"endDate": "2021-10-14 17:00",
			"subplots": "Setor 05",
			"area": "5.1385",
			"volume": "200",
			"product": "Kyleo, SILWET L-77",
			"quantity": "10.277 L, 0.514 L",
			"dosage": "2.0 L/hak 0.1 L/ha",
			"concentration": "1.0 L/100L, 0.05 L/100L",
			"ground": "",
			"activeSubs": "glifosato (sal de isopropilamónio) metoxi-poli-propil-heptametiltrisiloxano",
			"notes":"",
			"updatedAt": "2021-07-15 16:18",
			"updatedBy": "Pedro Lourenço"
		}
	},
	{
		"spray":
		{
			"id": "410483",
			"exportable": "Sim",
			"recommendation": "Sim",
			"initDate": "2021-10-14 08:00",
			"endDate": "2021-10-14 17:00",
			"subplots": "Setor 25, Setor 28",
			"area": "12.354",
			"volume": "1000",
			"product": "CUPROCOL, Solubor DF",
			"quantity": "49.416 L, 37.062 kg",
			"dosage": "4.0 L/ha, 3.0 kg/ha",
			"concentration": "0.4 L/100L, 0.3 kg/100L",
			"ground": "",
			"activeSubs": "Cobre",
			"notes":"",
			"updatedAt": "2021-10-14 11:41",
			"updatedBy": "Pedro Lourenço"
		}
	},
	{
		"spray":
		{
			"id": "329460",
			"exportable": "Sim",
			"recommendation": "Sim",
			"initDate": "2021-07-13 06:00",
			"endDate": "2021-07-16 14:00",
			"subplots": "Armazém",
			"area": "0",
			"volume": "",
			"product": "",
			"quantity": "",
			"dosage": "",
			"concentration": "",
			"ground": "",
			"activeSubs": "",
			"notes":"",
			"updatedAt": "2021-07-15 16:18",
			"updatedBy": "Pedro Lourenço"
		}
	}

]
